Metadata-Version: 1.0
Name: uvoauth
Version: 0.6
Summary: Oauth client for uvhttp
Home-page: https://github.com/justinbarrick/uvoauth
Author: UNKNOWN
Author-email: UNKNOWN
License: UNKNOWN
Platform: UNKNOWN
